{
    "Byron Rodriguez": {
        "image": "assets/images/1.jpg",
        "place": "palamaner",
        "amount": "10000",
        "installment": "100"
    },
    "Kristin Holmes": {
        "image": "assets/images/2.jpg",
        "place": "palamaner",
        "amount": "10000",
        "installment": "100"
    },
    "Everett Wagner": {
        "image": "assets/images/3.jpg",
        "place": "palamaner",
        "amount": "10000",
        "installment": "100"
    },
    "Roberto Bowman": {
        "image": "assets/images/4.jpg",
        "place": "palamaner",
        "amount": "10000",
        "installment": "100"
    },
    "Dale Day": {
        "image": "assets/images/5.jpg",
        "place": "palamaner",
        "amount": "40000",
        "installment": "400"
    },
    "Reginald Kelley": {
        "image": "assets/images/6.jpg",
        "place": "palamaner",
        "amount": "20000",
        "installment": "200"
    },
    "Darryl Richards": {
        "image": "assets/images/7.jpg",
        "place": "nagamangalam",
        "amount": "50000",
        "installment": "500"
    },
    "Terry Larson": {
        "image": "assets/images/8.jpg",
        "place": "chinnur",
        "amount": "100000",
        "installment": "1000"
    }
}